pycse/PYCSE.py
pycse/README.org
pycse/SKILL.md
pycse/__init__.py
pycse/beginner.py
pycse/cli.py
pycse/colab.py
pycse/colors.py
pycse/hashcache.py
pycse/lisp.py
pycse/mcp.py
pycse/orgmode.py
pycse/plotly.py
pycse/pyroxy.py
pycse/supyrvisor.py
pycse/utils.py
pycse/.claude/settings.local.json
pycse/examples/Active_Surrogate_Demo.ipynb
pycse/examples/DPOSE_Demo.ipynb
pycse/examples/KAN_Demo.ipynb
pycse/examples/KfoldNN_Demo.ipynb
pycse/examples/LeafModel_Demo.ipynb
pycse/examples/NNBR_Demo.ipynb
pycse/examples/NNGMM_Demo.ipynb
pycse/examples/Pyroxy_Demo.ipynb
pycse/examples/README.md
pycse/examples/Regression_Functions_Demo.ipynb
pycse/examples/Supyrvisor_Demo.ipynb
pycse/examples/UQ_Comparison_Demo.ipynb
pycse/examples/llpr_demo.ipynb
pycse/examples/llpr_study.ipynb
pycse/examples/nflows_regressor_examples.ipynb
pycse/examples/.claude/settings.local.json
pycse/images/bvp-nonlinear-2.png
pycse/images/bvp-pycse.png
pycse/sklearn/__init__.py
pycse/sklearn/dpose.py
pycse/sklearn/kan.py
pycse/sklearn/kfoldnn.py
pycse/sklearn/leaf_model.py
pycse/sklearn/lhc.py
pycse/sklearn/llpr_regressor.py
pycse/sklearn/lr_uq.py
pycse/sklearn/nflows_regressor.py
pycse/sklearn/nnbr.py
pycse/sklearn/nngmm.py
pycse/sklearn/optimizers.py
pycse/sklearn/surface_response.py
pycse/sklearn/.claude/settings.local.json
pycse/sklearn/tests/test_5d_analysis.py
pycse/sklearn/tests/test_5d_padding.py
pycse/sklearn/tests/test_cinn.py
pycse/sklearn/tests/test_cinn_debug.py
pycse/sklearn/tests/test_cinn_fixed.py
pycse/sklearn/tests/test_conditional_flow_context.py
pycse/sklearn/tests/test_convergence.py
pycse/sklearn/tests/test_debug_linear.py
pycse/sklearn/tests/test_final_comprehensive.py
pycse/sklearn/tests/test_final_fix.py
pycse/sklearn/tests/test_heteroskedastic.py
pycse/sklearn/tests/test_inn.py
pycse/sklearn/tests/test_invertibility.py
pycse/sklearn/tests/test_performance.py
pycse/sklearn/tests/test_permutation_analysis.py
pycse/sklearn/tests/test_quick_verify.py
pycse/tests/conftest.py
pycse-2.7.0.dist-info/METADATA
pycse-2.7.0.dist-info/WHEEL
pycse-2.7.0.dist-info/entry_points.txt
pycse-2.7.0.dist-info/licenses/LICENSE
pycse-2.7.0.dist-info/RECORD
