Metadata-Version: 2.1
Name: pycse
Version: 2.7.0
Summary: python computations in science and engineering
Author-email: John Kitchin <jkitchin@andrew.cmu.edu>
License: GPL-3.0-or-later
Requires-Python: >=3.9
Requires-Dist: click
Requires-Dist: dill
Requires-Dist: flax>=0.7.0
Requires-Dist: gmr
Requires-Dist: ipython
Requires-Dist: jax>=0.4.0
Requires-Dist: jaxlib>=0.4.0
Requires-Dist: joblib
Requires-Dist: matplotlib
Requires-Dist: networkx
Requires-Dist: numdifftools
Requires-Dist: numpy
Requires-Dist: optax>=0.1.0
Requires-Dist: orjson
Requires-Dist: pandas
Requires-Dist: pydoe3
Requires-Dist: requests
Requires-Dist: scikit-learn>=1.0.0
Requires-Dist: scipy
Requires-Dist: tabulate
Provides-Extra: test
Requires-Dist: coverage>=7.0; extra == 'test'
Requires-Dist: kaleido; extra == 'test'
Requires-Dist: plotly>=5.0; extra == 'test'
Requires-Dist: pytest-cov>=4.0; extra == 'test'
Requires-Dist: pytest-xdist>=3.0; extra == 'test'
Requires-Dist: pytest>=7.0; extra == 'test'
Requires-Dist: seaborn>=0.11.0; extra == 'test'
